starcat/__init__.py
starcat/build_consensus_reference.py
starcat/current_references.tsv
starcat/starcat.py
starcat/utils.py
starcatpy-1.0.9.dist-info/LICENSE
starcatpy-1.0.9.dist-info/METADATA
starcatpy-1.0.9.dist-info/WHEEL
starcatpy-1.0.9.dist-info/entry_points.txt
starcatpy-1.0.9.dist-info/top_level.txt
starcatpy-1.0.9.dist-info/RECORD
