Metadata-Version: 2.1
Name: starcatpy
Version: 1.0.9
Summary: Implements *CellAnnotator (aka *CAT/starCAT), annotating scRNA-Seq with predefined gene expression programs
Home-page: https://github.com/immunogenomics/starCAT
Author: Dylan Kotliar, Michelle Curtis
Author-email: dylkot@gmail.com, curtism@broadinstitute.org
Project-URL: Bug Tracker, https://github.com/immunogenomics/starCAT/issues
Classifier: Programming Language :: Python :: 3
Classifier: License :: OSI Approved :: MIT License
Classifier: Operating System :: OS Independent
License-File: LICENSE
Requires-Dist: scikit-learn>=1.0
Requires-Dist: anndata
Requires-Dist: pandas
Requires-Dist: numpy
Requires-Dist: scipy
Requires-Dist: pyyaml
Requires-Dist: requests
